{
  "hash": "8d94b16c6d5a9452b51346a798249e3f",
  "result": {
    "engine": "knitr",
    "markdown": "---\ntitle: \"Class 14: Meta-Analyses\"\nbibliography: ../references.bib\n---\n\n\n\n\n\n\n::: {.callout-caution}\n## Ups, there is no content here yet. \n\nAll materials, slides and assignments will be uploaded on the day of the class 🕖 \n:::\n\n\n",
    "supporting": [],
    "filters": [
      "rmarkdown/pagebreak.lua"
    ],
    "includes": {},
    "engineDependencies": {},
    "preserve": {},
    "postProcess": true
  }
}